odoo8_addon_base_headers_webkit-8.0.1.0.0-py2.7-nspkg.pth
odoo_addons/base_headers_webkit/__openerp__.py
odoo_addons/base_headers_webkit/base_headers_data.xml
odoo_addons/base_headers_webkit/__init__.py
odoo_addons/base_headers_webkit/README.rst
odoo8_addon_base_headers_webkit-8.0.1.0.0.dist-info/top_level.txt
odoo8_addon_base_headers_webkit-8.0.1.0.0.dist-info/WHEEL
odoo8_addon_base_headers_webkit-8.0.1.0.0.dist-info/RECORD
odoo8_addon_base_headers_webkit-8.0.1.0.0.dist-info/metadata.json
odoo8_addon_base_headers_webkit-8.0.1.0.0.dist-info/DESCRIPTION.rst
odoo8_addon_base_headers_webkit-8.0.1.0.0.dist-info/METADATA
odoo8_addon_base_headers_webkit-8.0.1.0.0.dist-info/namespace_packages.txt
